CHANGELOG.txt
LICENCE.txt
MANIFEST.in
README.md
setup.py
.pythonlibs/lib/python3.10/site-packages/cython.py
.pythonlibs/lib/python3.10/site-packages/Cython/CodeWriter.py
.pythonlibs/lib/python3.10/site-packages/Cython/Coverage.py
.pythonlibs/lib/python3.10/site-packages/Cython/Debugging.py
.pythonlibs/lib/python3.10/site-packages/Cython/Shadow.py
.pythonlibs/lib/python3.10/site-packages/Cython/StringIOTree.py
.pythonlibs/lib/python3.10/site-packages/Cython/TestUtils.py
.pythonlibs/lib/python3.10/site-packages/Cython/Utils.py
.pythonlibs/lib/python3.10/site-packages/Cython/__init__.py
.pythonlibs/lib/python3.10/site-packages/Cython-3.0.7.dist-info/COPYING.txt
.pythonlibs/lib/python3.10/site-packages/Cython-3.0.7.dist-info/LICENSE.txt
.pythonlibs/lib/python3.10/site-packages/Cython-3.0.7.dist-info/entry_points.txt
.pythonlibs/lib/python3.10/site-packages/Cython-3.0.7.dist-info/top_level.txt
.pythonlibs/lib/python3.10/site-packages/Cython/Build/BuildExecutable.py
.pythonlibs/lib/python3.10/site-packages/Cython/Build/Cythonize.py
.pythonlibs/lib/python3.10/site-packages/Cython/Build/Dependencies.py
.pythonlibs/lib/python3.10/site-packages/Cython/Build/Distutils.py
.pythonlibs/lib/python3.10/site-packages/Cython/Build/Inline.py
.pythonlibs/lib/python3.10/site-packages/Cython/Build/IpythonMagic.py
.pythonlibs/lib/python3.10/site-packages/Cython/Build/__init__.py
.pythonlibs/lib/python3.10/site-packages/Cython/Build/Tests/TestCyCache.py
.pythonlibs/lib/python3.10/site-packages/Cython/Build/Tests/TestCythonizeArgsParser.py
.pythonlibs/lib/python3.10/site-packages/Cython/Build/Tests/TestDependencies.py
.pythonlibs/lib/python3.10/site-packages/Cython/Build/Tests/TestInline.py
.pythonlibs/lib/python3.10/site-packages/Cython/Build/Tests/TestIpythonMagic.py
.pythonlibs/lib/python3.10/site-packages/Cython/Build/Tests/TestRecythonize.py
.pythonlibs/lib/python3.10/site-packages/Cython/Build/Tests/TestStripLiterals.py
.pythonlibs/lib/python3.10/site-packages/Cython/Build/Tests/__init__.py
.pythonlibs/lib/python3.10/site-packages/Cython/Compiler/AnalysedTreeTransforms.py
.pythonlibs/lib/python3.10/site-packages/Cython/Compiler/Annotate.py
.pythonlibs/lib/python3.10/site-packages/Cython/Compiler/AutoDocTransforms.py
.pythonlibs/lib/python3.10/site-packages/Cython/Compiler/Buffer.py
.pythonlibs/lib/python3.10/site-packages/FileEncryption-0.1.6-py3.10.egg-info/SOURCES.txt
.pythonlibs/lib/python3.10/site-packages/FileEncryption-0.1.6-py3.10.egg-info/dependency_links.txt
.pythonlibs/lib/python3.10/site-packages/FileEncryption-0.1.6-py3.10.egg-info/installed-files.txt
.pythonlibs/lib/python3.10/site-packages/FileEncryption-0.1.6-py3.10.egg-info/requires.txt
.pythonlibs/lib/python3.10/site-packages/FileEncryption-0.1.6-py3.10.egg-info/top_level.txt
.pythonlibs/lib/python3.10/site-packages/certifi-2023.11.17.dist-info/top_level.txt
.pythonlibs/lib/python3.10/site-packages/charset_normalizer-3.3.2.dist-info/entry_points.txt
.pythonlibs/lib/python3.10/site-packages/charset_normalizer-3.3.2.dist-info/top_level.txt
.pythonlibs/lib/python3.10/site-packages/idna-3.6.dist-info/LICENSE.md
.pythonlibs/lib/python3.10/site-packages/markdown_it_py-3.0.0.dist-info/entry_points.txt
.pythonlibs/lib/python3.10/site-packages/pyarmor-8.4.6.dist-info/entry_points.txt
.pythonlibs/lib/python3.10/site-packages/pyarmor-8.4.6.dist-info/top_level.txt
.pythonlibs/lib/python3.10/site-packages/pyarmor.cli.core-5.4.3.dist-info/top_level.txt
.pythonlibs/lib/python3.10/site-packages/pygments-2.17.2.dist-info/entry_points.txt
.pythonlibs/lib/python3.10/site-packages/requests-2.31.0.dist-info/top_level.txt
.pythonlibs/lib/python3.10/site-packages/urllib3-2.1.0.dist-info/licenses/LICENSE.txt
PyBookAgents.egg-info/PKG-INFO
PyBookAgents.egg-info/SOURCES.txt
PyBookAgents.egg-info/dependency_links.txt
PyBookAgents.egg-info/not-zip-safe
PyBookAgents.egg-info/top_level.txt