Metadata-Version: 2.1
Name: PyBookAgents
Version: 0.0.1.dev0
Summary: Random user agents generator for Facebook. It has 4 options: Dalvik, iPhone, Android, and Random (it's either Android or iPhone)
Home-page: https://facebook.com/sintxcs
Author: Sintacs Ao
Author-email: sintacs@isnotdev.com
License: MIT
Project-URL: GitHub, https://github.com/sintxcs
Platform: UNKNOWN
Classifier: Development Status :: 5 - Production/Stable
Classifier: Intended Audience :: Education
Classifier: Operating System :: Microsoft :: Windows :: Windows 10
Classifier: License :: OSI Approved :: MIT License
Classifier: Programming Language :: Python :: 3
License-File: LICENCE.txt
